hasura_ndc/__init__.py
hasura_ndc/connector.py
hasura_ndc/errors.py
hasura_ndc/function_connector.py
hasura_ndc/instrumentation.py
hasura_ndc/main.py
hasura_ndc/models.py
hasura_ndc/server.py
hasura_ndc-0.38.dist-info/METADATA
hasura_ndc-0.38.dist-info/WHEEL
hasura_ndc-0.38.dist-info/top_level.txt
hasura_ndc-0.38.dist-info/RECORD
