Metadata-Version: 2.1
Name: hasura-ndc
Version: 0.38
Summary: A Hasura Data Connector SDK
Author: Tristen Harr
Author-email: tristen.harr@hasura.io
License: Apache License 2.0
Classifier: Programming Language :: Python :: 3
Classifier: License :: OSI Approved :: Apache Software License
Classifier: Operating System :: OS Independent
Requires-Dist: pydantic<3.0.0,>=2.7.0
Requires-Dist: typing-extensions<5.0.0,>=4.11.0
Requires-Dist: fastapi>=0.110.2
Requires-Dist: uvicorn>=0.29.0
Requires-Dist: opentelemetry-api<2.0.0,>=1.20.0
Requires-Dist: opentelemetry-exporter-otlp<2.0.0,>=1.20.0
Requires-Dist: opentelemetry-instrumentation-fastapi>=0.44b0
Requires-Dist: opentelemetry-instrumentation-logging>=0.44b0
Requires-Dist: opentelemetry-instrumentation-requests>=0.44b0
Requires-Dist: opentelemetry-propagator-b3<2.0.0,>=1.20.0
